datasette_export_database/__init__.py
datasette_export_database-0.2.1.dist-info/LICENSE
datasette_export_database-0.2.1.dist-info/METADATA
datasette_export_database-0.2.1.dist-info/WHEEL
datasette_export_database-0.2.1.dist-info/entry_points.txt
datasette_export_database-0.2.1.dist-info/top_level.txt
datasette_export_database-0.2.1.dist-info/RECORD
