Metadata-Version: 2.1
Name: datasette-export-database
Version: 0.2.1
Summary: Export a copy of a SQLite database on demand
Author: Simon Willison
License: Apache-2.0
Project-URL: Homepage, https://github.com/datasette/datasette-export-database
Project-URL: Changelog, https://github.com/datasette/datasette-export-database/releases
Project-URL: Issues, https://github.com/datasette/datasette-export-database/issues
Project-URL: CI, https://github.com/datasette/datasette-export-database/actions
Classifier: Framework :: Datasette
Classifier: License :: OSI Approved :: Apache Software License
Requires-Python: >=3.8
License-File: LICENSE
Requires-Dist: datasette
Provides-Extra: test
Requires-Dist: pytest ; extra == 'test'
Requires-Dist: pytest-asyncio ; extra == 'test'
